pylsewave/__init__.py
pylsewave/bcs.py
pylsewave/cynum.cp35-win_amd64.pyd
pylsewave/fdm.py
pylsewave/interpolate.py
pylsewave/mesh.py
pylsewave/nonlinearsolvers.py
pylsewave/optimiz.py
pylsewave/pdes.py
pylsewave/postprocessing.py
pylsewave/pwconsts.py
pylsewave/pwutils.py
pylsewave/viz.py
test/__init__.py
test/test_pytdma.py
pylsewave-1.0.1.dist-info/LICENSE
pylsewave-1.0.1.dist-info/METADATA
pylsewave-1.0.1.dist-info/WHEEL
pylsewave-1.0.1.dist-info/top_level.txt
pylsewave-1.0.1.dist-info/RECORD
