Metadata-Version: 2.1
Name: pylsewave
Version: 1.0.1
Summary: A python package for pulse wave dynamics and/or any hyperbolic system of PDEs
Home-page: https://giorag.bitbucket.io/pylsewave/pyw_doc.html
Author: Georgios E. Ragkousis
Author-email: giorgosragos@gmail.com
License: GNU GPL v3.0
Keywords: pdes fdm pulsewave blood-vessels
Platform: UNKNOWN
Classifier: Development Status :: 4 - Beta
Classifier: Intended Audience :: Education
Classifier: Intended Audience :: Developers
Classifier: Intended Audience :: Healthcare Industry
Classifier: Intended Audience :: Information Technology
Classifier: Intended Audience :: Science/Research
Classifier: Topic :: Scientific/Engineering
Classifier: Topic :: Scientific/Engineering :: Mathematics
Classifier: License :: OSI Approved :: GNU General Public License v3 (GPLv3)
Classifier: Programming Language :: Python :: 3.4
Classifier: Programming Language :: Python :: 3.5
Classifier: Environment :: Win32 (MS Windows)
Requires: numpy
Requires: scipy
Requires: matplotlib
Requires-Dist: numpy
Requires-Dist: scipy
Requires-Dist: matplotlib
